nscctj_redis_session/RedisSessionStore.py
nscctj_redis_session/__init__.py
th_redis_session-0.9.0.dist-info/LICENSE
th_redis_session-0.9.0.dist-info/METADATA
th_redis_session-0.9.0.dist-info/WHEEL
th_redis_session-0.9.0.dist-info/top_level.txt
th_redis_session-0.9.0.dist-info/RECORD
