Metadata-Version: 2.1
Name: th-redis-session
Version: 0.9.0
Summary: A package to support redis session store in django project
Author: nscctj
Author-email: lics@nscc-tj.cn
Classifier: Programming Language :: Python :: 3
Classifier: License :: OSI Approved :: MIT License
Classifier: Operating System :: OS Independent
Requires-Python: >=3.7
License-File: LICENSE
Requires-Dist: Django (>=3.2)
Requires-Dist: django-redis (>=5.2)
